batteryinfo-0.1.5.dist-info/METADATA
batteryinfo-0.1.5.dist-info/WHEEL
batteryinfo-0.1.5.dist-info/licenses/LICENSE-MIT
batteryinfo/__init__.py
batteryinfo/__init__.pyi
batteryinfo/py.typed
batteryinfo/batteryinfo.pypy310-pp73-win_amd64.pyd
batteryinfo-0.1.5.dist-info/RECORD
