Metadata-Version: 2.4
Name: batteryinfo
Version: 0.1.5
Classifier: Programming Language :: Python :: 3
Classifier: Programming Language :: Rust
License-File: LICENSE-MIT
Summary: A Python module written in rust for battery information
Keywords: python,module,battery,information
Author: Dave Johnson <dave@thisdavej.com>
Author-email: Dave Johnson <dave@thisdavej.com>
License: MIT
Project-URL: Homepage, https://github.com/thisdavej/batteryinfo-py
